{"00":{"FlightDetails":{"Details":[[{"Origin":{"AirportCode":"BLR","CityName":"Bangalore","AirportName":"Bengaluru International Airport","date_time":"2020-12-14T17:55:00.000+05:30","DateTime":"2020-12-14 17:55:00","date":"2020-12-14","time":"17:55:00","FDTV":1607948700,"OriginTerminal":null},"Destination":{"AirportCode":"DEL","CityName":"Delhi","AirportName":"Indira Gandhi International Airport","date_time":"2020-12-14T20:40:00.000+05:30","DateTime":"2020-12-14 20:40:00","date":"2020-12-14","time":"20:40:00","FATV":1607958600,"DestinationTerminal":"3"},"Duration":"2 Hrs 45 Mins ","OperatorCode":"UK","OperatorName":"Air vistara","FlightNumber":"820","is_leg":false,"CabinClass":"E","Attr":{"Baggage":"1 Piece","CabinBaggage":0,"AvailableSeats":"6"}}]]},"Price":{"Fare_Type":"Regular Fare","PassengerBreakup":{"ADT":{"PassengerCount":1,"BasePrice":5820,"Tax":817,"TotalPrice":6637}},"Currency":"INR","TotalDisplayFare":6637,"PriceBreakup":{"Tax":817,"BasicFare":5820,"Tax_Details":{"Other_Tax":687,"YR":130},"CommissionEarned":0,"PLBEarned":0,"TdsOnCommission":0,"TdsOnPLB":0,"AgentCommission":0,"AgentTdsOnCommision":0}},"Attr":{"IsRefundable":0,"AirlineRemark":""},"HoldTicket":true,"ResultToken":"2659a3f850056572ae1b171f45a20389*_*1*_*sybQlqdMyzsSk8I1","api_original_price_details":{"TotalDisplayFare":6637,"api_currency":"INR","AgentCommission":0,"BasicFare":5820,"Tax":817},"FareDetails":{"Currency":"INR","BaseFare":5820,"Tax":817,"PublishedFare":6637,"AgentCommission":0,"AgentTdsOnCommision":0,"OfferedFare":6637,"AgentCommissionPerc":0},"PassengerFareBreakdown":{"ADT":{"PassengerCount":1,"Tax":817,"TotalPrice":6637,"BaseFare":5820}}},"01":{"FlightDetails":{"Details":[[{"Origin":{"AirportCode":"BLR","CityName":"Bangalore","AirportName":"Bengaluru International Airport","date_time":"2020-12-14T15:10:00.000+05:30","DateTime":"2020-12-14 15:10:00","date":"2020-12-14","time":"15:10:00","FDTV":1607938800,"OriginTerminal":null},"Destination":{"AirportCode":"DEL","CityName":"Delhi","AirportName":"Indira Gandhi International Airport","date_time":"2020-12-14T17:55:00.000+05:30","DateTime":"2020-12-14 17:55:00","date":"2020-12-14","time":"17:55:00","FATV":1607948700,"DestinationTerminal":"3"},"Duration":"2 Hrs 45 Mins ","OperatorCode":"UK","OperatorName":"Air vistara","FlightNumber":"812","is_leg":false,"CabinClass":"V","Attr":{"Baggage":"15 Kilograms","CabinBaggage":0,"AvailableSeats":"9"}}]]},"Price":{"Fare_Type":"Regular Fare","PassengerBreakup":{"ADT":{"PassengerCount":1,"BasePrice":6320,"Tax":842,"TotalPrice":7162}},"Currency":"INR","TotalDisplayFare":7162,"PriceBreakup":{"Tax":842,"BasicFare":6320,"Tax_Details":{"Other_Tax":712,"YR":130},"CommissionEarned":0,"PLBEarned":0,"TdsOnCommission":0,"TdsOnPLB":0,"AgentCommission":0,"AgentTdsOnCommision":0}},"Attr":{"IsRefundable":1,"AirlineRemark":""},"HoldTicket":true,"ResultToken":"2659a3f850056572ae1b171f45a20389*_*2*_*W5EQCxp6CIVVAjKq","api_original_price_details":{"TotalDisplayFare":7162,"api_currency":"INR","AgentCommission":0,"BasicFare":6320,"Tax":842},"FareDetails":{"Currency":"INR","BaseFare":6320,"Tax":842,"PublishedFare":7162,"AgentCommission":0,"AgentTdsOnCommision":0,"OfferedFare":7162,"AgentCommissionPerc":0},"PassengerFareBreakdown":{"ADT":{"PassengerCount":1,"Tax":842,"TotalPrice":7162,"BaseFare":6320}}},"02":{"FlightDetails":{"Details":[[{"Origin":{"AirportCode":"BLR","CityName":"Bangalore","AirportName":"Bengaluru International Airport","date_time":"2020-12-14T19:30:00.000+05:30","DateTime":"2020-12-14 19:30:00","date":"2020-12-14","time":"19:30:00","FDTV":1607954400,"OriginTerminal":null},"Destination":{"AirportCode":"DEL","CityName":"Delhi","AirportName":"Indira Gandhi International Airport","date_time":"2020-12-14T22:15:00.000+05:30","DateTime":"2020-12-14 22:15:00","date":"2020-12-14","time":"22:15:00","FATV":1607964300,"DestinationTerminal":"3"},"Duration":"2 Hrs 45 Mins ","OperatorCode":"UK","OperatorName":"Air vistara","FlightNumber":"818","is_leg":false,"CabinClass":"V","Attr":{"Baggage":"15 Kilograms","CabinBaggage":0,"AvailableSeats":"5"}}]]},"Price":{"Fare_Type":"Regular Fare","PassengerBreakup":{"ADT":{"PassengerCount":1,"BasePrice":6320,"Tax":842,"TotalPrice":7162}},"Currency":"INR","TotalDisplayFare":7162,"PriceBreakup":{"Tax":842,"BasicFare":6320,"Tax_Details":{"Other_Tax":712,"YR":130},"CommissionEarned":0,"PLBEarned":0,"TdsOnCommission":0,"TdsOnPLB":0,"AgentCommission":0,"AgentTdsOnCommision":0}},"Attr":{"IsRefundable":1,"AirlineRemark":""},"HoldTicket":true,"ResultToken":"2659a3f850056572ae1b171f45a20389*_*3*_*E7bDWbguQCXjqkhv","api_original_price_details":{"TotalDisplayFare":7162,"api_currency":"INR","AgentCommission":0,"BasicFare":6320,"Tax":842},"FareDetails":{"Currency":"INR","BaseFare":6320,"Tax":842,"PublishedFare":7162,"AgentCommission":0,"AgentTdsOnCommision":0,"OfferedFare":7162,"AgentCommissionPerc":0},"PassengerFareBreakdown":{"ADT":{"PassengerCount":1,"Tax":842,"TotalPrice":7162,"BaseFare":6320}}},"03":{"FlightDetails":{"Details":[[{"Origin":{"AirportCode":"BLR","CityName":"Bangalore","AirportName":"Bengaluru International Airport","date_time":"2020-12-14T20:30:00.000+05:30","DateTime":"2020-12-14 20:30:00","date":"2020-12-14","time":"20:30:00","FDTV":1607958000,"OriginTerminal":null},"Destination":{"AirportCode":"BOM","CityName":"Mumbai","AirportName":"Chhatrapati Shivaji International Airport","date_time":"2020-12-14T21:55:00.000+05:30","DateTime":"2020-12-14 21:55:00","date":"2020-12-14","time":"21:55:00","FATV":1607963100,"DestinationTerminal":"2"},"Duration":"1 Hr 25 Mins ","OperatorCode":"UK","OperatorName":"Air vistara","FlightNumber":"854","is_leg":false,"CabinClass":"O","Attr":{"Baggage":"1 Piece","CabinBaggage":0,"AvailableSeats":"9"}},{"Origin":{"AirportCode":"BOM","CityName":"Mumbai","AirportName":"Chhatrapati Shivaji International Airport","date_time":"2020-12-15T17:00:00.000+05:30","DateTime":"2020-12-15 17:00:00","date":"2020-12-15","time":"17:00:00","FDTV":1607945400,"OriginTerminal":"2"},"Destination":{"AirportCode":"DEL","CityName":"Delhi","AirportName":"Indira Gandhi International Airport","date_time":"2020-12-15T19:10:00.000+05:30","DateTime":"2020-12-15 19:10:00","date":"2020-12-15","time":"19:10:00","FATV":1607953200,"DestinationTerminal":"3"},"Duration":"2 Hrs 10 Mins ","OperatorCode":"UK","OperatorName":"Air vistara","FlightNumber":"910","is_leg":false,"CabinClass":"O","Attr":{"Baggage":"1 Piece","CabinBaggage":0,"AvailableSeats":"9"}}]],"0":{"lay_over_time":["22 Hrs 40 Mins "]}},"Price":{"Fare_Type":"Regular Fare","PassengerBreakup":{"ADT":{"PassengerCount":1,"BasePrice":7330,"Tax":1029,"TotalPrice":8359}},"Currency":"INR","TotalDisplayFare":8359,"PriceBreakup":{"Tax":1029,"BasicFare":7330,"Tax_Details":{"Other_Tax":769,"YR":260},"CommissionEarned":0,"PLBEarned":0,"TdsOnCommission":0,"TdsOnPLB":0,"AgentCommission":0,"AgentTdsOnCommision":0}},"Attr":{"IsRefundable":0,"AirlineRemark":""},"HoldTicket":true,"ResultToken":"2659a3f850056572ae1b171f45a20389*_*4*_*TFSubPKv6Q4s4bBz","api_original_price_details":{"TotalDisplayFare":8359,"api_currency":"INR","AgentCommission":0,"BasicFare":7330,"Tax":1029},"FareDetails":{"Currency":"INR","BaseFare":7330,"Tax":1029,"PublishedFare":8359,"AgentCommission":0,"AgentTdsOnCommision":0,"OfferedFare":8359,"AgentCommissionPerc":0},"PassengerFareBreakdown":{"ADT":{"PassengerCount":1,"Tax":1029,"TotalPrice":8359,"BaseFare":7330}}},"04":{"FlightDetails":{"Details":[[{"Origin":{"AirportCode":"BLR","CityName":"Bangalore","AirportName":"Bengaluru International Airport","date_time":"2020-12-14T21:00:00.000+05:30","DateTime":"2020-12-14 21:00:00","date":"2020-12-14","time":"21:00:00","FDTV":1607959800,"OriginTerminal":null},"Destination":{"AirportCode":"DEL","CityName":"Delhi","AirportName":"Indira Gandhi International Airport","date_time":"2020-12-14T23:45:00.000+05:30","DateTime":"2020-12-14 23:45:00","date":"2020-12-14","time":"23:45:00","FATV":1607969700,"DestinationTerminal":"3"},"Duration":"2 Hrs 45 Mins ","OperatorCode":"AI","OperatorName":"Air india","FlightNumber":"502","is_leg":false,"CabinClass":"U","Attr":{"Baggage":"25 Kilograms","CabinBaggage":0,"AvailableSeats":"9"}}]]},"Price":{"Fare_Type":"Regular Fare","PassengerBreakup":{"ADT":{"PassengerCount":1,"BasePrice":8000,"Tax":968,"TotalPrice":8968}},"Currency":"INR","TotalDisplayFare":8968,"PriceBreakup":{"Tax":968,"BasicFare":8000,"Tax_Details":{"Other_Tax":798,"YR":170},"CommissionEarned":0,"PLBEarned":0,"TdsOnCommission":0,"TdsOnPLB":0,"AgentCommission":0,"AgentTdsOnCommision":0}},"Attr":{"IsRefundable":1,"AirlineRemark":""},"HoldTicket":true,"ResultToken":"2659a3f850056572ae1b171f45a20389*_*5*_*GwGe6grHnrIfIARp","api_original_price_details":{"TotalDisplayFare":8968,"api_currency":"INR","AgentCommission":0,"BasicFare":8000,"Tax":968},"FareDetails":{"Currency":"INR","BaseFare":8000,"Tax":968,"PublishedFare":8968,"AgentCommission":0,"AgentTdsOnCommision":0,"OfferedFare":8968,"AgentCommissionPerc":0},"PassengerFareBreakdown":{"ADT":{"PassengerCount":1,"Tax":968,"TotalPrice":8968,"BaseFare":8000}}},"05":{"FlightDetails":{"Details":[[{"Origin":{"AirportCode":"BLR","CityName":"Bangalore","AirportName":"Bengaluru International Airport","date_time":"2020-12-14T20:30:00.000+05:30","DateTime":"2020-12-14 20:30:00","date":"2020-12-14","time":"20:30:00","FDTV":1607958000,"OriginTerminal":null},"Destination":{"AirportCode":"BOM","CityName":"Mumbai","AirportName":"Chhatrapati Shivaji International Airport","date_time":"2020-12-14T21:55:00.000+05:30","DateTime":"2020-12-14 21:55:00","date":"2020-12-14","time":"21:55:00","FATV":1607963100,"DestinationTerminal":"2"},"Duration":"1 Hr 25 Mins ","OperatorCode":"UK","OperatorName":"Air vistara","FlightNumber":"854","is_leg":false,"CabinClass":"O","Attr":{"Baggage":"1 Piece","CabinBaggage":0,"AvailableSeats":"9"}},{"Origin":{"AirportCode":"BOM","CityName":"Mumbai","AirportName":"Chhatrapati Shivaji International Airport","date_time":"2020-12-15T06:30:00.000+05:30","DateTime":"2020-12-15 06:30:00","date":"2020-12-15","time":"06:30:00","FDTV":1607907600,"OriginTerminal":"2"},"Destination":{"AirportCode":"GOI","CityName":"Goa","AirportName":"Dabolim Airport","date_time":"2020-12-15T07:40:00.000+05:30","DateTime":"2020-12-15 07:40:00","date":"2020-12-15","time":"07:40:00","FATV":1607911800,"DestinationTerminal":null},"Duration":"1 Hr 10 Mins ","OperatorCode":"UK","OperatorName":"Air vistara","FlightNumber":"861","is_leg":false,"CabinClass":"O","Attr":{"Baggage":"1 Piece","CabinBaggage":0,"AvailableSeats":"9"}},{"Origin":{"AirportCode":"GOI","CityName":"Goa","AirportName":"Dabolim Airport","date_time":"2020-12-15T08:25:00.000+05:30","DateTime":"2020-12-15 08:25:00","date":"2020-12-15","time":"08:25:00","FDTV":1607914500,"OriginTerminal":null},"Destination":{"AirportCode":"DEL","CityName":"Delhi","AirportName":"Indira Gandhi International Airport","date_time":"2020-12-15T11:10:00.000+05:30","DateTime":"2020-12-15 11:10:00","date":"2020-12-15","time":"11:10:00","FATV":1607924400,"DestinationTerminal":"3"},"Duration":"2 Hrs 45 Mins ","OperatorCode":"UK","OperatorName":"Air vistara","FlightNumber":"856","is_leg":false,"CabinClass":"O","Attr":{"Baggage":"1 Piece","CabinBaggage":0,"AvailableSeats":"9"}}]],"0":{"lay_over_time":["11 Hrs 10 Mins ","4 Hrs 40 Mins "]}},"Price":{"Fare_Type":"Regular Fare","PassengerBreakup":{"ADT":{"PassengerCount":1,"BasePrice":9615,"Tax":1279,"TotalPrice":10894}},"Currency":"INR","TotalDisplayFare":10894,"PriceBreakup":{"Tax":1279,"BasicFare":9615,"Tax_Details":{"Other_Tax":889,"YR":390},"CommissionEarned":0,"PLBEarned":0,"TdsOnCommission":0,"TdsOnPLB":0,"AgentCommission":0,"AgentTdsOnCommision":0}},"Attr":{"IsRefundable":0,"AirlineRemark":""},"HoldTicket":true,"ResultToken":"2659a3f850056572ae1b171f45a20389*_*6*_*HlwiSN0pKRHO6Fpy","api_original_price_details":{"TotalDisplayFare":10894,"api_currency":"INR","AgentCommission":0,"BasicFare":9615,"Tax":1279},"FareDetails":{"Currency":"INR","BaseFare":9615,"Tax":1279,"PublishedFare":10894,"AgentCommission":0,"AgentTdsOnCommision":0,"OfferedFare":10894,"AgentCommissionPerc":0},"PassengerFareBreakdown":{"ADT":{"PassengerCount":1,"Tax":1279,"TotalPrice":10894,"BaseFare":9615}}},"06":{"FlightDetails":{"Details":[[{"Origin":{"AirportCode":"BLR","CityName":"Bangalore","AirportName":"Bengaluru International Airport","date_time":"2020-12-14T20:30:00.000+05:30","DateTime":"2020-12-14 20:30:00","date":"2020-12-14","time":"20:30:00","FDTV":1607958000,"OriginTerminal":null},"Destination":{"AirportCode":"BOM","CityName":"Mumbai","AirportName":"Chhatrapati Shivaji International Airport","date_time":"2020-12-14T21:55:00.000+05:30","DateTime":"2020-12-14 21:55:00","date":"2020-12-14","time":"21:55:00","FATV":1607963100,"DestinationTerminal":"2"},"Duration":"1 Hr 25 Mins ","OperatorCode":"UK","OperatorName":"Air vistara","FlightNumber":"854","is_leg":false,"CabinClass":"O","Attr":{"Baggage":"1 Piece","CabinBaggage":0,"AvailableSeats":"9"}},{"Origin":{"AirportCode":"BOM","CityName":"Mumbai","AirportName":"Chhatrapati Shivaji International Airport","date_time":"2020-12-15T12:30:00.000+05:30","DateTime":"2020-12-15 12:30:00","date":"2020-12-15","time":"12:30:00","FDTV":1607929200,"OriginTerminal":"2"},"Destination":{"AirportCode":"GOI","CityName":"Goa","AirportName":"Dabolim Airport","date_time":"2020-12-15T13:45:00.000+05:30","DateTime":"2020-12-15 13:45:00","date":"2020-12-15","time":"13:45:00","FATV":1607933700,"DestinationTerminal":null},"Duration":"1 Hr 15 Mins ","OperatorCode":"UK","OperatorName":"Air vistara","FlightNumber":"841","is_leg":false,"CabinClass":"O","Attr":{"Baggage":"1 Piece","CabinBaggage":0,"AvailableSeats":"9"}},{"Origin":{"AirportCode":"GOI","CityName":"Goa","AirportName":"Dabolim Airport","date_time":"2020-12-15T14:30:00.000+05:30","DateTime":"2020-12-15 14:30:00","date":"2020-12-15","time":"14:30:00","FDTV":1607936400,"OriginTerminal":null},"Destination":{"AirportCode":"DEL","CityName":"Delhi","AirportName":"Indira Gandhi International Airport","date_time":"2020-12-15T17:00:00.000+05:30","DateTime":"2020-12-15 17:00:00","date":"2020-12-15","time":"17:00:00","FATV":1607945400,"DestinationTerminal":"3"},"Duration":"2 Hrs 30 Mins ","OperatorCode":"UK","OperatorName":"Air vistara","FlightNumber":"848","is_leg":false,"CabinClass":"E","Attr":{"Baggage":"1 Piece","CabinBaggage":0,"AvailableSeats":"9"}}]],"0":{"lay_over_time":["17 Hrs 15 Mins ","4 Hrs 30 Mins "]}},"Price":{"Fare_Type":"Regular Fare","PassengerBreakup":{"ADT":{"PassengerCount":1,"BasePrice":10135,"Tax":1305,"TotalPrice":11440}},"Currency":"INR","TotalDisplayFare":11440,"PriceBreakup":{"Tax":1305,"BasicFare":10135,"Tax_Details":{"Other_Tax":915,"YR":390},"CommissionEarned":0,"PLBEarned":0,"TdsOnCommission":0,"TdsOnPLB":0,"AgentCommission":0,"AgentTdsOnCommision":0}},"Attr":{"IsRefundable":0,"AirlineRemark":""},"HoldTicket":true,"ResultToken":"2659a3f850056572ae1b171f45a20389*_*7*_*W1TLO2ccOxVo6uDC","api_original_price_details":{"TotalDisplayFare":11440,"api_currency":"INR","AgentCommission":0,"BasicFare":10135,"Tax":1305},"FareDetails":{"Currency":"INR","BaseFare":10135,"Tax":1305,"PublishedFare":11440,"AgentCommission":0,"AgentTdsOnCommision":0,"OfferedFare":11440,"AgentCommissionPerc":0},"PassengerFareBreakdown":{"ADT":{"PassengerCount":1,"Tax":1305,"TotalPrice":11440,"BaseFare":10135}}},"07":{"FlightDetails":{"Details":[[{"Origin":{"AirportCode":"BLR","CityName":"Bangalore","AirportName":"Bengaluru International Airport","date_time":"2020-12-14T20:30:00.000+05:30","DateTime":"2020-12-14 20:30:00","date":"2020-12-14","time":"20:30:00","FDTV":1607958000,"OriginTerminal":null},"Destination":{"AirportCode":"BOM","CityName":"Mumbai","AirportName":"Chhatrapati Shivaji International Airport","date_time":"2020-12-14T21:55:00.000+05:30","DateTime":"2020-12-14 21:55:00","date":"2020-12-14","time":"21:55:00","FATV":1607963100,"DestinationTerminal":"2"},"Duration":"1 Hr 25 Mins ","OperatorCode":"UK","OperatorName":"Air vistara","FlightNumber":"854","is_leg":false,"CabinClass":"O","Attr":{"Baggage":"1 Piece","CabinBaggage":0,"AvailableSeats":"9"}},{"Origin":{"AirportCode":"BOM","CityName":"Mumbai","AirportName":"Chhatrapati Shivaji International Airport","date_time":"2020-12-15T06:30:00.000+05:30","DateTime":"2020-12-15 06:30:00","date":"2020-12-15","time":"06:30:00","FDTV":1607907600,"OriginTerminal":"2"},"Destination":{"AirportCode":"GOI","CityName":"Goa","AirportName":"Dabolim Airport","date_time":"2020-12-15T07:40:00.000+05:30","DateTime":"2020-12-15 07:40:00","date":"2020-12-15","time":"07:40:00","FATV":1607911800,"DestinationTerminal":null},"Duration":"1 Hr 10 Mins ","OperatorCode":"UK","OperatorName":"Air vistara","FlightNumber":"861","is_leg":false,"CabinClass":"O","Attr":{"Baggage":"1 Piece","CabinBaggage":0,"AvailableSeats":"9"}},{"Origin":{"AirportCode":"GOI","CityName":"Goa","AirportName":"Dabolim Airport","date_time":"2020-12-15T14:30:00.000+05:30","DateTime":"2020-12-15 14:30:00","date":"2020-12-15","time":"14:30:00","FDTV":1607936400,"OriginTerminal":null},"Destination":{"AirportCode":"DEL","CityName":"Delhi","AirportName":"Indira Gandhi International Airport","date_time":"2020-12-15T17:00:00.000+05:30","DateTime":"2020-12-15 17:00:00","date":"2020-12-15","time":"17:00:00","FATV":1607945400,"DestinationTerminal":"3"},"Duration":"2 Hrs 30 Mins ","OperatorCode":"UK","OperatorName":"Air vistara","FlightNumber":"848","is_leg":false,"CabinClass":"E","Attr":{"Baggage":"1 Piece","CabinBaggage":0,"AvailableSeats":"9"}}]],"0":{"lay_over_time":["11 Hrs 10 Mins ","10 Hrs 30 Mins "]}},"Price":{"Fare_Type":"Regular Fare","PassengerBreakup":{"ADT":{"PassengerCount":1,"BasePrice":10135,"Tax":1305,"TotalPrice":11440}},"Currency":"INR","TotalDisplayFare":11440,"PriceBreakup":{"Tax":1305,"BasicFare":10135,"Tax_Details":{"Other_Tax":915,"YR":390},"CommissionEarned":0,"PLBEarned":0,"TdsOnCommission":0,"TdsOnPLB":0,"AgentCommission":0,"AgentTdsOnCommision":0}},"Attr":{"IsRefundable":0,"AirlineRemark":""},"HoldTicket":true,"ResultToken":"2659a3f850056572ae1b171f45a20389*_*8*_*YO1OnX8y58cS4lUL","api_original_price_details":{"TotalDisplayFare":11440,"api_currency":"INR","AgentCommission":0,"BasicFare":10135,"Tax":1305},"FareDetails":{"Currency":"INR","BaseFare":10135,"Tax":1305,"PublishedFare":11440,"AgentCommission":0,"AgentTdsOnCommision":0,"OfferedFare":11440,"AgentCommissionPerc":0},"PassengerFareBreakdown":{"ADT":{"PassengerCount":1,"Tax":1305,"TotalPrice":11440,"BaseFare":10135}}},"08":{"FlightDetails":{"Details":[[{"Origin":{"AirportCode":"BLR","CityName":"Bangalore","AirportName":"Bengaluru International Airport","date_time":"2020-12-14T20:30:00.000+05:30","DateTime":"2020-12-14 20:30:00","date":"2020-12-14","time":"20:30:00","FDTV":1607958000,"OriginTerminal":null},"Destination":{"AirportCode":"BOM","CityName":"Mumbai","AirportName":"Chhatrapati Shivaji International Airport","date_time":"2020-12-14T21:55:00.000+05:30","DateTime":"2020-12-14 21:55:00","date":"2020-12-14","time":"21:55:00","FATV":1607963100,"DestinationTerminal":"2"},"Duration":"1 Hr 25 Mins ","OperatorCode":"UK","OperatorName":"Air vistara","FlightNumber":"854","is_leg":false,"CabinClass":"V","Attr":{"Baggage":"15 Kilograms","CabinBaggage":0,"AvailableSeats":"9"}},{"Origin":{"AirportCode":"BOM","CityName":"Mumbai","AirportName":"Chhatrapati Shivaji International Airport","date_time":"2020-12-15T13:35:00.000+05:30","DateTime":"2020-12-15 13:35:00","date":"2020-12-15","time":"13:35:00","FDTV":1607933100,"OriginTerminal":"2"},"Destination":{"AirportCode":"DEL","CityName":"Delhi","AirportName":"Indira Gandhi International Airport","date_time":"2020-12-15T15:40:00.000+05:30","DateTime":"2020-12-15 15:40:00","date":"2020-12-15","time":"15:40:00","FATV":1607940600,"DestinationTerminal":"3"},"Duration":"2 Hrs 5 Mins ","OperatorCode":"UK","OperatorName":"Air vistara","FlightNumber":"944","is_leg":false,"CabinClass":"Q","Attr":{"Baggage":"15 Kilograms","CabinBaggage":0,"AvailableSeats":"9"}}]],"0":{"lay_over_time":["19 Hrs 10 Mins "]}},"Price":{"Fare_Type":"Regular Fare","PassengerBreakup":{"ADT":{"PassengerCount":1,"BasePrice":10550,"Tax":1190,"TotalPrice":11740}},"Currency":"INR","TotalDisplayFare":11740,"PriceBreakup":{"Tax":1190,"BasicFare":10550,"Tax_Details":{"Other_Tax":930,"YR":260},"CommissionEarned":0,"PLBEarned":0,"TdsOnCommission":0,"TdsOnPLB":0,"AgentCommission":0,"AgentTdsOnCommision":0}},"Attr":{"IsRefundable":1,"AirlineRemark":""},"HoldTicket":true,"ResultToken":"2659a3f850056572ae1b171f45a20389*_*9*_*fyCKE4qx3CT02Vtb","api_original_price_details":{"TotalDisplayFare":11740,"api_currency":"INR","AgentCommission":0,"BasicFare":10550,"Tax":1190},"FareDetails":{"Currency":"INR","BaseFare":10550,"Tax":1190,"PublishedFare":11740,"AgentCommission":0,"AgentTdsOnCommision":0,"OfferedFare":11740,"AgentCommissionPerc":0},"PassengerFareBreakdown":{"ADT":{"PassengerCount":1,"Tax":1190,"TotalPrice":11740,"BaseFare":10550}}},"09":{"FlightDetails":{"Details":[[{"Origin":{"AirportCode":"BLR","CityName":"Bangalore","AirportName":"Bengaluru International Airport","date_time":"2020-12-14T20:30:00.000+05:30","DateTime":"2020-12-14 20:30:00","date":"2020-12-14","time":"20:30:00","FDTV":1607958000,"OriginTerminal":null},"Destination":{"AirportCode":"BOM","CityName":"Mumbai","AirportName":"Chhatrapati Shivaji International Airport","date_time":"2020-12-14T21:55:00.000+05:30","DateTime":"2020-12-14 21:55:00","date":"2020-12-14","time":"21:55:00","FATV":1607963100,"DestinationTerminal":"2"},"Duration":"1 Hr 25 Mins ","OperatorCode":"UK","OperatorName":"Air vistara","FlightNumber":"854","is_leg":false,"CabinClass":"V","Attr":{"Baggage":"15 Kilograms","CabinBaggage":0,"AvailableSeats":"9"}},{"Origin":{"AirportCode":"BOM","CityName":"Mumbai","AirportName":"Chhatrapati Shivaji International Airport","date_time":"2020-12-15T15:45:00.000+05:30","DateTime":"2020-12-15 15:45:00","date":"2020-12-15","time":"15:45:00","FDTV":1607940900,"OriginTerminal":"2"},"Destination":{"AirportCode":"DEL","CityName":"Delhi","AirportName":"Indira Gandhi International Airport","date_time":"2020-12-15T18:00:00.000+05:30","DateTime":"2020-12-15 18:00:00","date":"2020-12-15","time":"18:00:00","FATV":1607949000,"DestinationTerminal":"3"},"Duration":"2 Hrs 15 Mins ","OperatorCode":"UK","OperatorName":"Air vistara","FlightNumber":"902","is_leg":false,"CabinClass":"Q","Attr":{"Baggage":"15 Kilograms","CabinBaggage":0,"AvailableSeats":"9"}}]],"0":{"lay_over_time":["21 Hrs 30 Mins "]}},"Price":{"Fare_Type":"Regular Fare","PassengerBreakup":{"ADT":{"PassengerCount":1,"BasePrice":10550,"Tax":1190,"TotalPrice":11740}},"Currency":"INR","TotalDisplayFare":11740,"PriceBreakup":{"Tax":1190,"BasicFare":10550,"Tax_Details":{"Other_Tax":930,"YR":260},"CommissionEarned":0,"PLBEarned":0,"TdsOnCommission":0,"TdsOnPLB":0,"AgentCommission":0,"AgentTdsOnCommision":0}},"Attr":{"IsRefundable":1,"AirlineRemark":""},"HoldTicket":true,"ResultToken":"2659a3f850056572ae1b171f45a20389*_*10*_*oaHuFYQqIU6rxglR","api_original_price_details":{"TotalDisplayFare":11740,"api_currency":"INR","AgentCommission":0,"BasicFare":10550,"Tax":1190},"FareDetails":{"Currency":"INR","BaseFare":10550,"Tax":1190,"PublishedFare":11740,"AgentCommission":0,"AgentTdsOnCommision":0,"OfferedFare":11740,"AgentCommissionPerc":0},"PassengerFareBreakdown":{"ADT":{"PassengerCount":1,"Tax":1190,"TotalPrice":11740,"BaseFare":10550}}},"010":{"FlightDetails":{"Details":[[{"Origin":{"AirportCode":"BLR","CityName":"Bangalore","AirportName":"Bengaluru International Airport","date_time":"2020-12-14T20:30:00.000+05:30","DateTime":"2020-12-14 20:30:00","date":"2020-12-14","time":"20:30:00","FDTV":1607958000,"OriginTerminal":null},"Destination":{"AirportCode":"BOM","CityName":"Mumbai","AirportName":"Chhatrapati Shivaji International Airport","date_time":"2020-12-14T21:55:00.000+05:30","DateTime":"2020-12-14 21:55:00","date":"2020-12-14","time":"21:55:00","FATV":1607963100,"DestinationTerminal":"2"},"Duration":"1 Hr 25 Mins ","OperatorCode":"UK","OperatorName":"Air vistara","FlightNumber":"854","is_leg":false,"CabinClass":"V","Attr":{"Baggage":"15 Kilograms","CabinBaggage":0,"AvailableSeats":"9"}},{"Origin":{"AirportCode":"BOM","CityName":"Mumbai","AirportName":"Chhatrapati Shivaji International Airport","date_time":"2020-12-15T09:50:00.000+05:30","DateTime":"2020-12-15 09:50:00","date":"2020-12-15","time":"09:50:00","FDTV":1607919600,"OriginTerminal":"2"},"Destination":{"AirportCode":"DEL","CityName":"Delhi","AirportName":"Indira Gandhi International Airport","date_time":"2020-12-15T12:00:00.000+05:30","DateTime":"2020-12-15 12:00:00","date":"2020-12-15","time":"12:00:00","FATV":1607927400,"DestinationTerminal":"3"},"Duration":"2 Hrs 10 Mins ","OperatorCode":"UK","OperatorName":"Air vistara","FlightNumber":"994","is_leg":false,"CabinClass":"W","Attr":{"Baggage":"15 Kilograms","CabinBaggage":0,"AvailableSeats":"9"}}]],"0":{"lay_over_time":["15 Hrs 30 Mins "]}},"Price":{"Fare_Type":"Regular Fare","PassengerBreakup":{"ADT":{"PassengerCount":1,"BasePrice":11150,"Tax":1220,"TotalPrice":12370}},"Currency":"INR","TotalDisplayFare":12370,"PriceBreakup":{"Tax":1220,"BasicFare":11150,"Tax_Details":{"Other_Tax":960,"YR":260},"CommissionEarned":0,"PLBEarned":0,"TdsOnCommission":0,"TdsOnPLB":0,"AgentCommission":0,"AgentTdsOnCommision":0}},"Attr":{"IsRefundable":1,"AirlineRemark":""},"HoldTicket":true,"ResultToken":"2659a3f850056572ae1b171f45a20389*_*11*_*FLrVQxxpeMQPfWw0","api_original_price_details":{"TotalDisplayFare":12370,"api_currency":"INR","AgentCommission":0,"BasicFare":11150,"Tax":1220},"FareDetails":{"Currency":"INR","BaseFare":11150,"Tax":1220,"PublishedFare":12370,"AgentCommission":0,"AgentTdsOnCommision":0,"OfferedFare":12370,"AgentCommissionPerc":0},"PassengerFareBreakdown":{"ADT":{"PassengerCount":1,"Tax":1220,"TotalPrice":12370,"BaseFare":11150}}},"011":{"FlightDetails":{"Details":[[{"Origin":{"AirportCode":"BLR","CityName":"Bangalore","AirportName":"Bengaluru International Airport","date_time":"2020-12-14T20:30:00.000+05:30","DateTime":"2020-12-14 20:30:00","date":"2020-12-14","time":"20:30:00","FDTV":1607958000,"OriginTerminal":null},"Destination":{"AirportCode":"BOM","CityName":"Mumbai","AirportName":"Chhatrapati Shivaji International Airport","date_time":"2020-12-14T21:55:00.000+05:30","DateTime":"2020-12-14 21:55:00","date":"2020-12-14","time":"21:55:00","FATV":1607963100,"DestinationTerminal":"2"},"Duration":"1 Hr 25 Mins ","OperatorCode":"UK","OperatorName":"Air vistara","FlightNumber":"854","is_leg":false,"CabinClass":"V","Attr":{"Baggage":"15 Kilograms","CabinBaggage":0,"AvailableSeats":"9"}},{"Origin":{"AirportCode":"BOM","CityName":"Mumbai","AirportName":"Chhatrapati Shivaji International Airport","date_time":"2020-12-15T20:40:00.000+05:30","DateTime":"2020-12-15 20:40:00","date":"2020-12-15","time":"20:40:00","FDTV":1607958600,"OriginTerminal":"2"},"Destination":{"AirportCode":"DEL","CityName":"Delhi","AirportName":"Indira Gandhi International Airport","date_time":"2020-12-15T22:45:00.000+05:30","DateTime":"2020-12-15 22:45:00","date":"2020-12-15","time":"22:45:00","FATV":1607966100,"DestinationTerminal":"3"},"Duration":"2 Hrs 5 Mins ","OperatorCode":"UK","OperatorName":"Air vistara","FlightNumber":"988","is_leg":false,"CabinClass":"W","Attr":{"Baggage":"15 Kilograms","CabinBaggage":0,"AvailableSeats":"9"}}]],"0":{"lay_over_time":["1 Day 2 Hrs 15 Mins "]}},"Price":{"Fare_Type":"Regular Fare","PassengerBreakup":{"ADT":{"PassengerCount":1,"BasePrice":11150,"Tax":1220,"TotalPrice":12370}},"Currency":"INR","TotalDisplayFare":12370,"PriceBreakup":{"Tax":1220,"BasicFare":11150,"Tax_Details":{"Other_Tax":960,"YR":260},"CommissionEarned":0,"PLBEarned":0,"TdsOnCommission":0,"TdsOnPLB":0,"AgentCommission":0,"AgentTdsOnCommision":0}},"Attr":{"IsRefundable":1,"AirlineRemark":""},"HoldTicket":true,"ResultToken":"2659a3f850056572ae1b171f45a20389*_*12*_*tPdJ7EKxdPAUZtEe","api_original_price_details":{"TotalDisplayFare":12370,"api_currency":"INR","AgentCommission":0,"BasicFare":11150,"Tax":1220},"FareDetails":{"Currency":"INR","BaseFare":11150,"Tax":1220,"PublishedFare":12370,"AgentCommission":0,"AgentTdsOnCommision":0,"OfferedFare":12370,"AgentCommissionPerc":0},"PassengerFareBreakdown":{"ADT":{"PassengerCount":1,"Tax":1220,"TotalPrice":12370,"BaseFare":11150}}},"012":{"FlightDetails":{"Details":[[{"Origin":{"AirportCode":"BLR","CityName":"Bangalore","AirportName":"Bengaluru International Airport","date_time":"2020-12-14T20:30:00.000+05:30","DateTime":"2020-12-14 20:30:00","date":"2020-12-14","time":"20:30:00","FDTV":1607958000,"OriginTerminal":null},"Destination":{"AirportCode":"BOM","CityName":"Mumbai","AirportName":"Chhatrapati Shivaji International Airport","date_time":"2020-12-14T21:55:00.000+05:30","DateTime":"2020-12-14 21:55:00","date":"2020-12-14","time":"21:55:00","FATV":1607963100,"DestinationTerminal":"2"},"Duration":"1 Hr 25 Mins ","OperatorCode":"UK","OperatorName":"Air vistara","FlightNumber":"854","is_leg":false,"CabinClass":"O","Attr":{"Baggage":"1 Piece","CabinBaggage":0,"AvailableSeats":"9"}},{"Origin":{"AirportCode":"BOM","CityName":"Mumbai","AirportName":"Chhatrapati Shivaji International Airport","date_time":"2020-12-15T08:05:00.000+05:30","DateTime":"2020-12-15 08:05:00","date":"2020-12-15","time":"08:05:00","FDTV":1607913300,"OriginTerminal":"2"},"Destination":{"AirportCode":"VNS","CityName":"Varanasi","AirportName":"Varanasi Airport","date_time":"2020-12-15T10:05:00.000+05:30","DateTime":"2020-12-15 10:05:00","date":"2020-12-15","time":"10:05:00","FATV":1607920500,"DestinationTerminal":null},"Duration":"2 Hrs ","OperatorCode":"UK","OperatorName":"Air vistara","FlightNumber":"621","is_leg":false,"CabinClass":"O","Attr":{"Baggage":"1 Piece","CabinBaggage":0,"AvailableSeats":"9"}},{"Origin":{"AirportCode":"VNS","CityName":"Varanasi","AirportName":"Varanasi Airport","date_time":"2020-12-15T15:25:00.000+05:30","DateTime":"2020-12-15 15:25:00","date":"2020-12-15","time":"15:25:00","FDTV":1607939700,"OriginTerminal":null},"Destination":{"AirportCode":"DEL","CityName":"Delhi","AirportName":"Indira Gandhi International Airport","date_time":"2020-12-15T16:55:00.000+05:30","DateTime":"2020-12-15 16:55:00","date":"2020-12-15","time":"16:55:00","FATV":1607945100,"DestinationTerminal":"3"},"Duration":"1 Hr 30 Mins ","OperatorCode":"UK","OperatorName":"Air vistara","FlightNumber":"674","is_leg":false,"CabinClass":"O","Attr":{"Baggage":"1 Piece","CabinBaggage":0,"AvailableSeats":"9"}}]],"0":{"lay_over_time":["13 Hrs 35 Mins ","8 Hrs 50 Mins "]}},"Price":{"Fare_Type":"Regular Fare","PassengerBreakup":{"ADT":{"PassengerCount":1,"BasePrice":11430,"Tax":1370,"TotalPrice":12800}},"Currency":"INR","TotalDisplayFare":12800,"PriceBreakup":{"Tax":1370,"BasicFare":11430,"Tax_Details":{"Other_Tax":980,"YR":390},"CommissionEarned":0,"PLBEarned":0,"TdsOnCommission":0,"TdsOnPLB":0,"AgentCommission":0,"AgentTdsOnCommision":0}},"Attr":{"IsRefundable":0,"AirlineRemark":""},"HoldTicket":true,"ResultToken":"2659a3f850056572ae1b171f45a20389*_*13*_*ixFvjCAMq7dr73uV","api_original_price_details":{"TotalDisplayFare":12800,"api_currency":"INR","AgentCommission":0,"BasicFare":11430,"Tax":1370},"FareDetails":{"Currency":"INR","BaseFare":11430,"Tax":1370,"PublishedFare":12800,"AgentCommission":0,"AgentTdsOnCommision":0,"OfferedFare":12800,"AgentCommissionPerc":0},"PassengerFareBreakdown":{"ADT":{"PassengerCount":1,"Tax":1370,"TotalPrice":12800,"BaseFare":11430}}},"013":{"FlightDetails":{"Details":[[{"Origin":{"AirportCode":"BLR","CityName":"Bangalore","AirportName":"Bengaluru International Airport","date_time":"2020-12-14T20:30:00.000+05:30","DateTime":"2020-12-14 20:30:00","date":"2020-12-14","time":"20:30:00","FDTV":1607958000,"OriginTerminal":null},"Destination":{"AirportCode":"BOM","CityName":"Mumbai","AirportName":"Chhatrapati Shivaji International Airport","date_time":"2020-12-14T21:55:00.000+05:30","DateTime":"2020-12-14 21:55:00","date":"2020-12-14","time":"21:55:00","FATV":1607963100,"DestinationTerminal":"2"},"Duration":"1 Hr 25 Mins ","OperatorCode":"UK","OperatorName":"Air vistara","FlightNumber":"854","is_leg":false,"CabinClass":"V","Attr":{"Baggage":"15 Kilograms","CabinBaggage":0,"AvailableSeats":"9"}},{"Origin":{"AirportCode":"BOM","CityName":"Mumbai","AirportName":"Chhatrapati Shivaji International Airport","date_time":"2020-12-15T07:30:00.000+05:30","DateTime":"2020-12-15 07:30:00","date":"2020-12-15","time":"07:30:00","FDTV":1607911200,"OriginTerminal":"2"},"Destination":{"AirportCode":"DEL","CityName":"Delhi","AirportName":"Indira Gandhi International Airport","date_time":"2020-12-15T09:40:00.000+05:30","DateTime":"2020-12-15 09:40:00","date":"2020-12-15","time":"09:40:00","FATV":1607919000,"DestinationTerminal":"3"},"Duration":"2 Hrs 10 Mins ","OperatorCode":"UK","OperatorName":"Air vistara","FlightNumber":"930","is_leg":false,"CabinClass":"W","Attr":{"Baggage":"15 Kilograms","CabinBaggage":0,"AvailableSeats":"9"}}]],"0":{"lay_over_time":["13 Hrs 10 Mins "]}},"Price":{"Fare_Type":"Regular Fare","PassengerBreakup":{"ADT":{"PassengerCount":1,"BasePrice":11650,"Tax":1245,"TotalPrice":12895}},"Currency":"INR","TotalDisplayFare":12895,"PriceBreakup":{"Tax":1245,"BasicFare":11650,"Tax_Details":{"Other_Tax":985,"YR":260},"CommissionEarned":0,"PLBEarned":0,"TdsOnCommission":0,"TdsOnPLB":0,"AgentCommission":0,"AgentTdsOnCommision":0}},"Attr":{"IsRefundable":1,"AirlineRemark":""},"HoldTicket":true,"ResultToken":"2659a3f850056572ae1b171f45a20389*_*14*_*Xj0TVfN4dehotk4a","api_original_price_details":{"TotalDisplayFare":12895,"api_currency":"INR","AgentCommission":0,"BasicFare":11650,"Tax":1245},"FareDetails":{"Currency":"INR","BaseFare":11650,"Tax":1245,"PublishedFare":12895,"AgentCommission":0,"AgentTdsOnCommision":0,"OfferedFare":12895,"AgentCommissionPerc":0},"PassengerFareBreakdown":{"ADT":{"PassengerCount":1,"Tax":1245,"TotalPrice":12895,"BaseFare":11650}}},"014":{"FlightDetails":{"Details":[[{"Origin":{"AirportCode":"BLR","CityName":"Bangalore","AirportName":"Bengaluru International Airport","date_time":"2020-12-14T20:30:00.000+05:30","DateTime":"2020-12-14 20:30:00","date":"2020-12-14","time":"20:30:00","FDTV":1607958000,"OriginTerminal":null},"Destination":{"AirportCode":"BOM","CityName":"Mumbai","AirportName":"Chhatrapati Shivaji International Airport","date_time":"2020-12-14T21:55:00.000+05:30","DateTime":"2020-12-14 21:55:00","date":"2020-12-14","time":"21:55:00","FATV":1607963100,"DestinationTerminal":"2"},"Duration":"1 Hr 25 Mins ","OperatorCode":"UK","OperatorName":"Air vistara","FlightNumber":"854","is_leg":false,"CabinClass":"V","Attr":{"Baggage":"15 Kilograms","CabinBaggage":0,"AvailableSeats":"9"}},{"Origin":{"AirportCode":"BOM","CityName":"Mumbai","AirportName":"Chhatrapati Shivaji International Airport","date_time":"2020-12-15T08:45:00.000+05:30","DateTime":"2020-12-15 08:45:00","date":"2020-12-15","time":"08:45:00","FDTV":1607915700,"OriginTerminal":"2"},"Destination":{"AirportCode":"DEL","CityName":"Delhi","AirportName":"Indira Gandhi International Airport","date_time":"2020-12-15T10:45:00.000+05:30","DateTime":"2020-12-15 10:45:00","date":"2020-12-15","time":"10:45:00","FATV":1607922900,"DestinationTerminal":"3"},"Duration":"2 Hrs ","OperatorCode":"UK","OperatorName":"Air vistara","FlightNumber":"970","is_leg":false,"CabinClass":"W","Attr":{"Baggage":"15 Kilograms","CabinBaggage":0,"AvailableSeats":"9"}}]],"0":{"lay_over_time":["14 Hrs 15 Mins "]}},"Price":{"Fare_Type":"Regular Fare","PassengerBreakup":{"ADT":{"PassengerCount":1,"BasePrice":11650,"Tax":1245,"TotalPrice":12895}},"Currency":"INR","TotalDisplayFare":12895,"PriceBreakup":{"Tax":1245,"BasicFare":11650,"Tax_Details":{"Other_Tax":985,"YR":260},"CommissionEarned":0,"PLBEarned":0,"TdsOnCommission":0,"TdsOnPLB":0,"AgentCommission":0,"AgentTdsOnCommision":0}},"Attr":{"IsRefundable":1,"AirlineRemark":""},"HoldTicket":true,"ResultToken":"2659a3f850056572ae1b171f45a20389*_*15*_*jNxbfkQcS0g0WlMw","api_original_price_details":{"TotalDisplayFare":12895,"api_currency":"INR","AgentCommission":0,"BasicFare":11650,"Tax":1245},"FareDetails":{"Currency":"INR","BaseFare":11650,"Tax":1245,"PublishedFare":12895,"AgentCommission":0,"AgentTdsOnCommision":0,"OfferedFare":12895,"AgentCommissionPerc":0},"PassengerFareBreakdown":{"ADT":{"PassengerCount":1,"Tax":1245,"TotalPrice":12895,"BaseFare":11650}}},"015":{"FlightDetails":{"Details":[[{"Origin":{"AirportCode":"BLR","CityName":"Bangalore","AirportName":"Bengaluru International Airport","date_time":"2020-12-14T20:30:00.000+05:30","DateTime":"2020-12-14 20:30:00","date":"2020-12-14","time":"20:30:00","FDTV":1607958000,"OriginTerminal":null},"Destination":{"AirportCode":"BOM","CityName":"Mumbai","AirportName":"Chhatrapati Shivaji International Airport","date_time":"2020-12-14T21:55:00.000+05:30","DateTime":"2020-12-14 21:55:00","date":"2020-12-14","time":"21:55:00","FATV":1607963100,"DestinationTerminal":"2"},"Duration":"1 Hr 25 Mins ","OperatorCode":"UK","OperatorName":"Air vistara","FlightNumber":"854","is_leg":false,"CabinClass":"V","Attr":{"Baggage":"15 Kilograms","CabinBaggage":0,"AvailableSeats":"9"}},{"Origin":{"AirportCode":"BOM","CityName":"Mumbai","AirportName":"Chhatrapati Shivaji International Airport","date_time":"2020-12-15T18:00:00.000+05:30","DateTime":"2020-12-15 18:00:00","date":"2020-12-15","time":"18:00:00","FDTV":1607949000,"OriginTerminal":"2"},"Destination":{"AirportCode":"DEL","CityName":"Delhi","AirportName":"Indira Gandhi International Airport","date_time":"2020-12-15T20:10:00.000+05:30","DateTime":"2020-12-15 20:10:00","date":"2020-12-15","time":"20:10:00","FATV":1607956800,"DestinationTerminal":"3"},"Duration":"2 Hrs 10 Mins ","OperatorCode":"UK","OperatorName":"Air vistara","FlightNumber":"996","is_leg":false,"CabinClass":"W","Attr":{"Baggage":"15 Kilograms","CabinBaggage":0,"AvailableSeats":"9"}}]],"0":{"lay_over_time":["23 Hrs 40 Mins "]}},"Price":{"Fare_Type":"Regular Fare","PassengerBreakup":{"ADT":{"PassengerCount":1,"BasePrice":11650,"Tax":1245,"TotalPrice":12895}},"Currency":"INR","TotalDisplayFare":12895,"PriceBreakup":{"Tax":1245,"BasicFare":11650,"Tax_Details":{"Other_Tax":985,"YR":260},"CommissionEarned":0,"PLBEarned":0,"TdsOnCommission":0,"TdsOnPLB":0,"AgentCommission":0,"AgentTdsOnCommision":0}},"Attr":{"IsRefundable":1,"AirlineRemark":""},"HoldTicket":true,"ResultToken":"2659a3f850056572ae1b171f45a20389*_*16*_*WqhOIIOKNVT2MlXQ","api_original_price_details":{"TotalDisplayFare":12895,"api_currency":"INR","AgentCommission":0,"BasicFare":11650,"Tax":1245},"FareDetails":{"Currency":"INR","BaseFare":11650,"Tax":1245,"PublishedFare":12895,"AgentCommission":0,"AgentTdsOnCommision":0,"OfferedFare":12895,"AgentCommissionPerc":0},"PassengerFareBreakdown":{"ADT":{"PassengerCount":1,"Tax":1245,"TotalPrice":12895,"BaseFare":11650}}},"016":{"FlightDetails":{"Details":[[{"Origin":{"AirportCode":"BLR","CityName":"Bangalore","AirportName":"Bengaluru International Airport","date_time":"2020-12-14T20:30:00.000+05:30","DateTime":"2020-12-14 20:30:00","date":"2020-12-14","time":"20:30:00","FDTV":1607958000,"OriginTerminal":null},"Destination":{"AirportCode":"BOM","CityName":"Mumbai","AirportName":"Chhatrapati Shivaji International Airport","date_time":"2020-12-14T21:55:00.000+05:30","DateTime":"2020-12-14 21:55:00","date":"2020-12-14","time":"21:55:00","FATV":1607963100,"DestinationTerminal":"2"},"Duration":"1 Hr 25 Mins ","OperatorCode":"UK","OperatorName":"Air vistara","FlightNumber":"854","is_leg":false,"CabinClass":"V","Attr":{"Baggage":"15 Kilograms","CabinBaggage":0,"AvailableSeats":"9"}},{"Origin":{"AirportCode":"BOM","CityName":"Mumbai","AirportName":"Chhatrapati Shivaji International Airport","date_time":"2020-12-15T19:40:00.000+05:30","DateTime":"2020-12-15 19:40:00","date":"2020-12-15","time":"19:40:00","FDTV":1607955000,"OriginTerminal":"2"},"Destination":{"AirportCode":"DEL","CityName":"Delhi","AirportName":"Indira Gandhi International Airport","date_time":"2020-12-15T21:45:00.000+05:30","DateTime":"2020-12-15 21:45:00","date":"2020-12-15","time":"21:45:00","FATV":1607962500,"DestinationTerminal":"3"},"Duration":"2 Hrs 5 Mins ","OperatorCode":"UK","OperatorName":"Air vistara","FlightNumber":"940","is_leg":false,"CabinClass":"W","Attr":{"Baggage":"15 Kilograms","CabinBaggage":0,"AvailableSeats":"9"}}]],"0":{"lay_over_time":["1 Day 1 Hr 15 Mins "]}},"Price":{"Fare_Type":"Regular Fare","PassengerBreakup":{"ADT":{"PassengerCount":1,"BasePrice":11650,"Tax":1245,"TotalPrice":12895}},"Currency":"INR","TotalDisplayFare":12895,"PriceBreakup":{"Tax":1245,"BasicFare":11650,"Tax_Details":{"Other_Tax":985,"YR":260},"CommissionEarned":0,"PLBEarned":0,"TdsOnCommission":0,"TdsOnPLB":0,"AgentCommission":0,"AgentTdsOnCommision":0}},"Attr":{"IsRefundable":1,"AirlineRemark":""},"HoldTicket":true,"ResultToken":"2659a3f850056572ae1b171f45a20389*_*17*_*q3IZjr4cIlKcxWKq","api_original_price_details":{"TotalDisplayFare":12895,"api_currency":"INR","AgentCommission":0,"BasicFare":11650,"Tax":1245},"FareDetails":{"Currency":"INR","BaseFare":11650,"Tax":1245,"PublishedFare":12895,"AgentCommission":0,"AgentTdsOnCommision":0,"OfferedFare":12895,"AgentCommissionPerc":0},"PassengerFareBreakdown":{"ADT":{"PassengerCount":1,"Tax":1245,"TotalPrice":12895,"BaseFare":11650}}},"017":{"FlightDetails":{"Details":[[{"Origin":{"AirportCode":"BLR","CityName":"Bangalore","AirportName":"Bengaluru International Airport","date_time":"2020-12-14T20:30:00.000+05:30","DateTime":"2020-12-14 20:30:00","date":"2020-12-14","time":"20:30:00","FDTV":1607958000,"OriginTerminal":null},"Destination":{"AirportCode":"BOM","CityName":"Mumbai","AirportName":"Chhatrapati Shivaji International Airport","date_time":"2020-12-14T21:55:00.000+05:30","DateTime":"2020-12-14 21:55:00","date":"2020-12-14","time":"21:55:00","FATV":1607963100,"DestinationTerminal":"2"},"Duration":"1 Hr 25 Mins ","OperatorCode":"UK","OperatorName":"Air vistara","FlightNumber":"854","is_leg":false,"CabinClass":"V","Attr":{"Baggage":"15 Kilograms","CabinBaggage":0,"AvailableSeats":"9"}},{"Origin":{"AirportCode":"BOM","CityName":"Mumbai","AirportName":"Chhatrapati Shivaji International Airport","date_time":"2020-12-15T16:00:00.000+05:30","DateTime":"2020-12-15 16:00:00","date":"2020-12-15","time":"16:00:00","FDTV":1607941800,"OriginTerminal":"2"},"Destination":{"AirportCode":"HYD","CityName":"Hyderabad","AirportName":"Rajiv Gandhi International Airport","date_time":"2020-12-15T17:30:00.000+05:30","DateTime":"2020-12-15 17:30:00","date":"2020-12-15","time":"17:30:00","FATV":1607947200,"DestinationTerminal":null},"Duration":"1 Hr 30 Mins ","OperatorCode":"UK","OperatorName":"Air vistara","FlightNumber":"877","is_leg":false,"CabinClass":"V","Attr":{"Baggage":"15 Kilograms","CabinBaggage":0,"AvailableSeats":"9"}},{"Origin":{"AirportCode":"HYD","CityName":"Hyderabad","AirportName":"Rajiv Gandhi International Airport","date_time":"2020-12-15T20:45:00.000+05:30","DateTime":"2020-12-15 20:45:00","date":"2020-12-15","time":"20:45:00","FDTV":1607958900,"OriginTerminal":null},"Destination":{"AirportCode":"DEL","CityName":"Delhi","AirportName":"Indira Gandhi International Airport","date_time":"2020-12-15T22:55:00.000+05:30","DateTime":"2020-12-15 22:55:00","date":"2020-12-15","time":"22:55:00","FATV":1607966700,"DestinationTerminal":"3"},"Duration":"2 Hrs 10 Mins ","OperatorCode":"UK","OperatorName":"Air vistara","FlightNumber":"870","is_leg":false,"CabinClass":"V","Attr":{"Baggage":"15 Kilograms","CabinBaggage":0,"AvailableSeats":"9"}}]],"0":{"lay_over_time":["21 Hrs ","6 Hrs 55 Mins "]}},"Price":{"Fare_Type":"Regular Fare","PassengerBreakup":{"ADT":{"PassengerCount":1,"BasePrice":12405,"Tax":1679,"TotalPrice":14084}},"Currency":"INR","TotalDisplayFare":14084,"PriceBreakup":{"Tax":1679,"BasicFare":12405,"Tax_Details":{"Other_Tax":1289,"YR":390},"CommissionEarned":0,"PLBEarned":0,"TdsOnCommission":0,"TdsOnPLB":0,"AgentCommission":0,"AgentTdsOnCommision":0}},"Attr":{"IsRefundable":1,"AirlineRemark":""},"HoldTicket":true,"ResultToken":"2659a3f850056572ae1b171f45a20389*_*18*_*YxhEa1rsad6tYkaU","api_original_price_details":{"TotalDisplayFare":14084,"api_currency":"INR","AgentCommission":0,"BasicFare":12405,"Tax":1679},"FareDetails":{"Currency":"INR","BaseFare":12405,"Tax":1679,"PublishedFare":14084,"AgentCommission":0,"AgentTdsOnCommision":0,"OfferedFare":14084,"AgentCommissionPerc":0},"PassengerFareBreakdown":{"ADT":{"PassengerCount":1,"Tax":1679,"TotalPrice":14084,"BaseFare":12405}}},"018":{"FlightDetails":{"Details":[[{"Origin":{"AirportCode":"BLR","CityName":"Bangalore","AirportName":"Bengaluru International Airport","date_time":"2020-12-14T20:30:00.000+05:30","DateTime":"2020-12-14 20:30:00","date":"2020-12-14","time":"20:30:00","FDTV":1607958000,"OriginTerminal":null},"Destination":{"AirportCode":"BOM","CityName":"Mumbai","AirportName":"Chhatrapati Shivaji International Airport","date_time":"2020-12-14T21:55:00.000+05:30","DateTime":"2020-12-14 21:55:00","date":"2020-12-14","time":"21:55:00","FATV":1607963100,"DestinationTerminal":"2"},"Duration":"1 Hr 25 Mins ","OperatorCode":"UK","OperatorName":"Air vistara","FlightNumber":"854","is_leg":false,"CabinClass":"O","Attr":{"Baggage":"1 Piece","CabinBaggage":0,"AvailableSeats":"9"}},{"Origin":{"AirportCode":"BOM","CityName":"Mumbai","AirportName":"Chhatrapati Shivaji International Airport","date_time":"2020-12-15T08:20:00.000+05:30","DateTime":"2020-12-15 08:20:00","date":"2020-12-15","time":"08:20:00","FDTV":1607914200,"OriginTerminal":"2"},"Destination":{"AirportCode":"MAA","CityName":"Chennai","AirportName":"Chennai Airport","date_time":"2020-12-15T10:15:00.000+05:30","DateTime":"2020-12-15 10:15:00","date":"2020-12-15","time":"10:15:00","FATV":1607921100,"DestinationTerminal":"1"},"Duration":"1 Hr 55 Mins ","OperatorCode":"UK","OperatorName":"Air vistara","FlightNumber":"825","is_leg":false,"CabinClass":"O","Attr":{"Baggage":"1 Piece","CabinBaggage":0,"AvailableSeats":"9"}},{"Origin":{"AirportCode":"MAA","CityName":"Chennai","AirportName":"Chennai Airport","date_time":"2020-12-15T11:55:00.000+05:30","DateTime":"2020-12-15 11:55:00","date":"2020-12-15","time":"11:55:00","FDTV":1607927100,"OriginTerminal":"1"},"Destination":{"AirportCode":"DEL","CityName":"Delhi","AirportName":"Indira Gandhi International Airport","date_time":"2020-12-15T14:45:00.000+05:30","DateTime":"2020-12-15 14:45:00","date":"2020-12-15","time":"14:45:00","FATV":1607937300,"DestinationTerminal":"3"},"Duration":"2 Hrs 50 Mins ","OperatorCode":"UK","OperatorName":"Air vistara","FlightNumber":"838","is_leg":false,"CabinClass":"O","Attr":{"Baggage":"1 Piece","CabinBaggage":0,"AvailableSeats":"9"}}]],"0":{"lay_over_time":["13 Hrs 45 Mins ","6 Hrs 25 Mins "]}},"Price":{"Fare_Type":"Regular Fare","PassengerBreakup":{"ADT":{"PassengerCount":1,"BasePrice":12935,"Tax":1445,"TotalPrice":14380}},"Currency":"INR","TotalDisplayFare":14380,"PriceBreakup":{"Tax":1445,"BasicFare":12935,"Tax_Details":{"Other_Tax":1055,"YR":390},"CommissionEarned":0,"PLBEarned":0,"TdsOnCommission":0,"TdsOnPLB":0,"AgentCommission":0,"AgentTdsOnCommision":0}},"Attr":{"IsRefundable":0,"AirlineRemark":""},"HoldTicket":true,"ResultToken":"2659a3f850056572ae1b171f45a20389*_*19*_*1ZqTxysDGXPpv70c","api_original_price_details":{"TotalDisplayFare":14380,"api_currency":"INR","AgentCommission":0,"BasicFare":12935,"Tax":1445},"FareDetails":{"Currency":"INR","BaseFare":12935,"Tax":1445,"PublishedFare":14380,"AgentCommission":0,"AgentTdsOnCommision":0,"OfferedFare":14380,"AgentCommissionPerc":0},"PassengerFareBreakdown":{"ADT":{"PassengerCount":1,"Tax":1445,"TotalPrice":14380,"BaseFare":12935}}},"019":{"FlightDetails":{"Details":[[{"Origin":{"AirportCode":"BLR","CityName":"Bangalore","AirportName":"Bengaluru International Airport","date_time":"2020-12-14T20:30:00.000+05:30","DateTime":"2020-12-14 20:30:00","date":"2020-12-14","time":"20:30:00","FDTV":1607958000,"OriginTerminal":null},"Destination":{"AirportCode":"BOM","CityName":"Mumbai","AirportName":"Chhatrapati Shivaji International Airport","date_time":"2020-12-14T21:55:00.000+05:30","DateTime":"2020-12-14 21:55:00","date":"2020-12-14","time":"21:55:00","FATV":1607963100,"DestinationTerminal":"2"},"Duration":"1 Hr 25 Mins ","OperatorCode":"UK","OperatorName":"Air vistara","FlightNumber":"854","is_leg":false,"CabinClass":"O","Attr":{"Baggage":"1 Piece","CabinBaggage":0,"AvailableSeats":"9"}},{"Origin":{"AirportCode":"BOM","CityName":"Mumbai","AirportName":"Chhatrapati Shivaji International Airport","date_time":"2020-12-15T08:20:00.000+05:30","DateTime":"2020-12-15 08:20:00","date":"2020-12-15","time":"08:20:00","FDTV":1607914200,"OriginTerminal":"2"},"Destination":{"AirportCode":"MAA","CityName":"Chennai","AirportName":"Chennai Airport","date_time":"2020-12-15T10:15:00.000+05:30","DateTime":"2020-12-15 10:15:00","date":"2020-12-15","time":"10:15:00","FATV":1607921100,"DestinationTerminal":"1"},"Duration":"1 Hr 55 Mins ","OperatorCode":"UK","OperatorName":"Air vistara","FlightNumber":"825","is_leg":false,"CabinClass":"O","Attr":{"Baggage":"1 Piece","CabinBaggage":0,"AvailableSeats":"9"}},{"Origin":{"AirportCode":"MAA","CityName":"Chennai","AirportName":"Chennai Airport","date_time":"2020-12-15T17:30:00.000+05:30","DateTime":"2020-12-15 17:30:00","date":"2020-12-15","time":"17:30:00","FDTV":1607947200,"OriginTerminal":"1"},"Destination":{"AirportCode":"DEL","CityName":"Delhi","AirportName":"Indira Gandhi International Airport","date_time":"2020-12-15T20:15:00.000+05:30","DateTime":"2020-12-15 20:15:00","date":"2020-12-15","time":"20:15:00","FATV":1607957100,"DestinationTerminal":"3"},"Duration":"2 Hrs 45 Mins ","OperatorCode":"UK","OperatorName":"Air vistara","FlightNumber":"834","is_leg":false,"CabinClass":"O","Attr":{"Baggage":"1 Piece","CabinBaggage":0,"AvailableSeats":"9"}}]],"0":{"lay_over_time":["13 Hrs 45 Mins ","11 Hrs 55 Mins "]}},"Price":{"Fare_Type":"Regular Fare","PassengerBreakup":{"ADT":{"PassengerCount":1,"BasePrice":12935,"Tax":1445,"TotalPrice":14380}},"Currency":"INR","TotalDisplayFare":14380,"PriceBreakup":{"Tax":1445,"BasicFare":12935,"Tax_Details":{"Other_Tax":1055,"YR":390},"CommissionEarned":0,"PLBEarned":0,"TdsOnCommission":0,"TdsOnPLB":0,"AgentCommission":0,"AgentTdsOnCommision":0}},"Attr":{"IsRefundable":0,"AirlineRemark":""},"HoldTicket":true,"ResultToken":"2659a3f850056572ae1b171f45a20389*_*20*_*N3hq0AthNqHj7L9x","api_original_price_details":{"TotalDisplayFare":14380,"api_currency":"INR","AgentCommission":0,"BasicFare":12935,"Tax":1445},"FareDetails":{"Currency":"INR","BaseFare":12935,"Tax":1445,"PublishedFare":14380,"AgentCommission":0,"AgentTdsOnCommision":0,"OfferedFare":14380,"AgentCommissionPerc":0},"PassengerFareBreakdown":{"ADT":{"PassengerCount":1,"Tax":1445,"TotalPrice":14380,"BaseFare":12935}}},"020":{"FlightDetails":{"Details":[[{"Origin":{"AirportCode":"BLR","CityName":"Bangalore","AirportName":"Bengaluru International Airport","date_time":"2020-12-14T20:30:00.000+05:30","DateTime":"2020-12-14 20:30:00","date":"2020-12-14","time":"20:30:00","FDTV":1607958000,"OriginTerminal":null},"Destination":{"AirportCode":"BOM","CityName":"Mumbai","AirportName":"Chhatrapati Shivaji International Airport","date_time":"2020-12-14T21:55:00.000+05:30","DateTime":"2020-12-14 21:55:00","date":"2020-12-14","time":"21:55:00","FATV":1607963100,"DestinationTerminal":"2"},"Duration":"1 Hr 25 Mins ","OperatorCode":"UK","OperatorName":"Air vistara","FlightNumber":"854","is_leg":false,"CabinClass":"V","Attr":{"Baggage":"15 Kilograms","CabinBaggage":0,"AvailableSeats":"9"}},{"Origin":{"AirportCode":"BOM","CityName":"Mumbai","AirportName":"Chhatrapati Shivaji International Airport","date_time":"2020-12-15T08:45:00.000+05:30","DateTime":"2020-12-15 08:45:00","date":"2020-12-15","time":"08:45:00","FDTV":1607915700,"OriginTerminal":"2"},"Destination":{"AirportCode":"HYD","CityName":"Hyderabad","AirportName":"Rajiv Gandhi International Airport","date_time":"2020-12-15T10:15:00.000+05:30","DateTime":"2020-12-15 10:15:00","date":"2020-12-15","time":"10:15:00","FATV":1607921100,"DestinationTerminal":null},"Duration":"1 Hr 30 Mins ","OperatorCode":"UK","OperatorName":"Air vistara","FlightNumber":"875","is_leg":false,"CabinClass":"V","Attr":{"Baggage":"15 Kilograms","CabinBaggage":0,"AvailableSeats":"9"}},{"Origin":{"AirportCode":"HYD","CityName":"Hyderabad","AirportName":"Rajiv Gandhi International Airport","date_time":"2020-12-15T17:30:00.000+05:30","DateTime":"2020-12-15 17:30:00","date":"2020-12-15","time":"17:30:00","FDTV":1607947200,"OriginTerminal":null},"Destination":{"AirportCode":"DEL","CityName":"Delhi","AirportName":"Indira Gandhi International Airport","date_time":"2020-12-15T19:45:00.000+05:30","DateTime":"2020-12-15 19:45:00","date":"2020-12-15","time":"19:45:00","FATV":1607955300,"DestinationTerminal":"3"},"Duration":"2 Hrs 15 Mins ","OperatorCode":"UK","OperatorName":"Air vistara","FlightNumber":"890","is_leg":false,"CabinClass":"V","Attr":{"Baggage":"15 Kilograms","CabinBaggage":0,"AvailableSeats":"9"}}]],"0":{"lay_over_time":["13 Hrs 45 Mins ","11 Hrs "]}},"Price":{"Fare_Type":"Regular Fare","PassengerBreakup":{"ADT":{"PassengerCount":1,"BasePrice":12405,"Tax":2187,"TotalPrice":14592}},"Currency":"INR","TotalDisplayFare":14592,"PriceBreakup":{"Tax":2187,"BasicFare":12405,"Tax_Details":{"Other_Tax":1797,"YR":390},"CommissionEarned":0,"PLBEarned":0,"TdsOnCommission":0,"TdsOnPLB":0,"AgentCommission":0,"AgentTdsOnCommision":0}},"Attr":{"IsRefundable":1,"AirlineRemark":""},"HoldTicket":true,"ResultToken":"2659a3f850056572ae1b171f45a20389*_*21*_*GjIyJognUFhduKqV","api_original_price_details":{"TotalDisplayFare":14592,"api_currency":"INR","AgentCommission":0,"BasicFare":12405,"Tax":2187},"FareDetails":{"Currency":"INR","BaseFare":12405,"Tax":2187,"PublishedFare":14592,"AgentCommission":0,"AgentTdsOnCommision":0,"OfferedFare":14592,"AgentCommissionPerc":0},"PassengerFareBreakdown":{"ADT":{"PassengerCount":1,"Tax":2187,"TotalPrice":14592,"BaseFare":12405}}},"021":{"FlightDetails":{"Details":[[{"Origin":{"AirportCode":"BLR","CityName":"Bangalore","AirportName":"Bengaluru International Airport","date_time":"2020-12-14T20:30:00.000+05:30","DateTime":"2020-12-14 20:30:00","date":"2020-12-14","time":"20:30:00","FDTV":1607958000,"OriginTerminal":null},"Destination":{"AirportCode":"BOM","CityName":"Mumbai","AirportName":"Chhatrapati Shivaji International Airport","date_time":"2020-12-14T21:55:00.000+05:30","DateTime":"2020-12-14 21:55:00","date":"2020-12-14","time":"21:55:00","FATV":1607963100,"DestinationTerminal":"2"},"Duration":"1 Hr 25 Mins ","OperatorCode":"UK","OperatorName":"Air vistara","FlightNumber":"854","is_leg":false,"CabinClass":"V","Attr":{"Baggage":"15 Kilograms","CabinBaggage":0,"AvailableSeats":"9"}},{"Origin":{"AirportCode":"BOM","CityName":"Mumbai","AirportName":"Chhatrapati Shivaji International Airport","date_time":"2020-12-15T08:45:00.000+05:30","DateTime":"2020-12-15 08:45:00","date":"2020-12-15","time":"08:45:00","FDTV":1607915700,"OriginTerminal":"2"},"Destination":{"AirportCode":"HYD","CityName":"Hyderabad","AirportName":"Rajiv Gandhi International Airport","date_time":"2020-12-15T10:15:00.000+05:30","DateTime":"2020-12-15 10:15:00","date":"2020-12-15","time":"10:15:00","FATV":1607921100,"DestinationTerminal":null},"Duration":"1 Hr 30 Mins ","OperatorCode":"UK","OperatorName":"Air vistara","FlightNumber":"875","is_leg":false,"CabinClass":"V","Attr":{"Baggage":"15 Kilograms","CabinBaggage":0,"AvailableSeats":"9"}},{"Origin":{"AirportCode":"HYD","CityName":"Hyderabad","AirportName":"Rajiv Gandhi International Airport","date_time":"2020-12-15T20:45:00.000+05:30","DateTime":"2020-12-15 20:45:00","date":"2020-12-15","time":"20:45:00","FDTV":1607958900,"OriginTerminal":null},"Destination":{"AirportCode":"DEL","CityName":"Delhi","AirportName":"Indira Gandhi International Airport","date_time":"2020-12-15T22:55:00.000+05:30","DateTime":"2020-12-15 22:55:00","date":"2020-12-15","time":"22:55:00","FATV":1607966700,"DestinationTerminal":"3"},"Duration":"2 Hrs 10 Mins ","OperatorCode":"UK","OperatorName":"Air vistara","FlightNumber":"870","is_leg":false,"CabinClass":"V","Attr":{"Baggage":"15 Kilograms","CabinBaggage":0,"AvailableSeats":"9"}}]],"0":{"lay_over_time":["13 Hrs 45 Mins ","14 Hrs 10 Mins "]}},"Price":{"Fare_Type":"Regular Fare","PassengerBreakup":{"ADT":{"PassengerCount":1,"BasePrice":12405,"Tax":2187,"TotalPrice":14592}},"Currency":"INR","TotalDisplayFare":14592,"PriceBreakup":{"Tax":2187,"BasicFare":12405,"Tax_Details":{"Other_Tax":1797,"YR":390},"CommissionEarned":0,"PLBEarned":0,"TdsOnCommission":0,"TdsOnPLB":0,"AgentCommission":0,"AgentTdsOnCommision":0}},"Attr":{"IsRefundable":1,"AirlineRemark":""},"HoldTicket":true,"ResultToken":"2659a3f850056572ae1b171f45a20389*_*22*_*RYTPPQ9CxHfN5sPQ","api_original_price_details":{"TotalDisplayFare":14592,"api_currency":"INR","AgentCommission":0,"BasicFare":12405,"Tax":2187},"FareDetails":{"Currency":"INR","BaseFare":12405,"Tax":2187,"PublishedFare":14592,"AgentCommission":0,"AgentTdsOnCommision":0,"OfferedFare":14592,"AgentCommissionPerc":0},"PassengerFareBreakdown":{"ADT":{"PassengerCount":1,"Tax":2187,"TotalPrice":14592,"BaseFare":12405}}}}